azure/mgmt/loadtesting/__init__.py
azure/mgmt/loadtesting/_configuration.py
azure/mgmt/loadtesting/_load_test_mgmt_client.py
azure/mgmt/loadtesting/_patch.py
azure/mgmt/loadtesting/_serialization.py
azure/mgmt/loadtesting/_vendor.py
azure/mgmt/loadtesting/_version.py
azure/mgmt/loadtesting/py.typed
azure/mgmt/loadtesting/aio/__init__.py
azure/mgmt/loadtesting/aio/_configuration.py
azure/mgmt/loadtesting/aio/_load_test_mgmt_client.py
azure/mgmt/loadtesting/aio/_patch.py
azure/mgmt/loadtesting/aio/operations/__init__.py
azure/mgmt/loadtesting/aio/operations/_load_tests_operations.py
azure/mgmt/loadtesting/aio/operations/_operations.py
azure/mgmt/loadtesting/aio/operations/_patch.py
azure/mgmt/loadtesting/aio/operations/_quotas_operations.py
azure/mgmt/loadtesting/models/__init__.py
azure/mgmt/loadtesting/models/_load_test_mgmt_client_enums.py
azure/mgmt/loadtesting/models/_models_py3.py
azure/mgmt/loadtesting/models/_patch.py
azure/mgmt/loadtesting/operations/__init__.py
azure/mgmt/loadtesting/operations/_load_tests_operations.py
azure/mgmt/loadtesting/operations/_operations.py
azure/mgmt/loadtesting/operations/_patch.py
azure/mgmt/loadtesting/operations/_quotas_operations.py
azure_mgmt_loadtesting-1.0.0.dist-info/LICENSE
azure_mgmt_loadtesting-1.0.0.dist-info/METADATA
azure_mgmt_loadtesting-1.0.0.dist-info/WHEEL
azure_mgmt_loadtesting-1.0.0.dist-info/top_level.txt
azure_mgmt_loadtesting-1.0.0.dist-info/RECORD
